gfss_microsoft/__init__.py
gfss_microsoft-0.0.2.dist-info/METADATA
gfss_microsoft-0.0.2.dist-info/WHEEL
gfss_microsoft-0.0.2.dist-info/top_level.txt
gfss_microsoft-0.0.2.dist-info/RECORD
