Metadata-Version: 2.1
Name: gfss-microsoft
Version: 0.0.2
Summary: gfss_microsoft
Home-page: https://www.placeholder
Author: John
Author-email: john.doe@mail.com
License: UNKNOWN
Project-URL: Bug Tracker, https://www.placeholder
Platform: UNKNOWN
Classifier: Programming Language :: Python :: 3
Classifier: License :: OSI Approved :: MIT License
Classifier: Operating System :: OS Independent
Requires-Python: >=3.6
